[
    {
        "table_name": "aux_accounts_by_channel_oozie",
        "non_nullable_col": "",
        "pk_col": "bor_account_id,channel",
        "ignore_col": "last_insert_timestamp"
    },
    {
        "table_name": "acct_mgr_position_pb",
        "non_nullable_col": "",
        "pk_col": "",
        "important_col": "acct_mgr_positn_id,branch_no,last_change_dt,to_dt",
        "ignore_col": "",
        "dupe_check_flag": "0"
    },
    {
        "table_name": "acct_pb_bal_base",
        "non_nullable_col": "",
        "pk_col": "",
        "important_col": "acct_id",
        "ignore_col": "",
        "dupe_check_flag": "0"
    },
    {
        "table_name": "anp_wbana_globalhit_src_oozie",
        "non_nullable_col": "",
        "pk_col": "",
        "important_col": "cif,date_time,post_pagename,ip",
        "ignore_col": "last_insert_timestamp",
        "dupe_check_flag": "0"
    },
    {
        "table_name": "consolidated_matches",
        "non_nullable_col": "",
        "pk_col": "",
        "important_col": "master_record_id",
        "ignore_col": "",
        "dupe_check_flag": "0"
    },
    {
        "table_name": "deterministic_matches",
        "non_nullable_col": "",
        "pk_col": "",
        "important_col": "other_party_id,other_system,mstr_rec_id",
        "ignore_col": "",
        "dupe_check_flag": "0"
    },
    {
        "table_name": "iiroc_6_month_supervision_report",
        "non_nullable_col": "order_number,order_sequence_id",
        "pk_col": "order_number,order_sequence_id",
        "ignore_col": "last_insert_timestamp"
    },
    {
        "table_name": "iiroc_test_migration",
        "tgt_table_cz_path": ["f'{cz_base_path}/rna_qa/{table_name}/'", "Y"],
        "op_table_cz_path": ["f'{cz_base_path}/rna_qa/onprem_{table_name}'", "Y"]
    },
    {
        "table_name": "investment_party_relationship",
        "non_nullable_col": "",
        "pk_col": "bor_account_id,party_surrogate_key,other_party_id,private_banking_indicator",
        "ignore_col": "last_insert_timestamp"
    },
    {
        "table_name": "pbprofit_contrib",
        "non_nullable_col": "",
        "pk_col": "acct_id",
        "important_col": "",
        "ignore_col": "last_insert_timestamp",
        "dupe_check_flag": "0"
    },
    {
        "table_name": "pb_finance_cust_acct_mgr_bal",
        "non_nullable_col": "",
        "pk_col": "",
        "important_col": "acct_id,cust_id",
        "ignore_col": "",
        "dupe_check_flag": "0"
    },
    {
        "table_name": "pb_finance_pers_acct_profit",
        "non_nullable_col": "",
        "pk_col": "",
        "important_col": "acct_id",
        "ignore_col": "",
        "dupe_check_flag": "0"
    },
    {
        "table_name": "pb_finance_pers_core_cash_profit",
        "non_nullable_col": "",
        "pk_col": "",
        "important_col": "acct_id,emplye_li",
        "ignore_col": "",
        "dupe_check_flag": "0"
    },
    {
        "table_name": "pb_finance_pers_core_od_profit",
        "non_nullable_col": "",
        "pk_col": "",
        "important_col": "acct_id",
        "ignore_col": "",
        "dupe_check_flag": "0"
    },
    {
        "table_name": "pb_finance_pers_core_splits_pb",
        "non_nullable_col": "",
        "pk_col": "",
        "important_col": "emplye_li",
        "ignore_col": "",
        "dupe_check_flag": "0"
    },
    {
        "table_name": "pb_finance_pers_creditcard_profit",
        "non_nullable_col": "",
        "pk_col": "",
        "important_col": "acct_id",
        "ignore_col": "",
        "dupe_check_flag": "0"
    },
    {
        "table_name": "pb_finance_pers_profit_pb",
        "non_nullable_col": "",
        "pk_col": "",
        "important_col": "emplye_li",
        "ignore_col": "",
        "dupe_check_flag": "0"
    },
    {
        "table_name": "prod_stg_miscellaneous_calldata_oozie",
        "non_nullable_col": "",
        "pk_col": "acct_no,callkey",
        "ignore_col": "last_insert_timestamp"
    },
    {
        "table_name": "prod_miscellaneous_logins_oozie",
        "non_nullable_col": "",
        "pk_col": "cust_id,rnm",
        "ignore_col": "last_insert_timestamp",
        "dupe_check_flag": "0"
    },
    {
        "table_name": "prod_stg_quotes_watchlists_oozie",
        "non_nullable_col": "",
        "pk_col": "visid,rnm",
        "ignore_col": "last_insert_timestamp",
        "dupe_check_flag": "0"
    },
    {
        "table_name": "referrals",
        "non_nullable_col": "lead_id",
        "pk_col": "lead_id,rnm",
        "ignore_col": "last_insert_timestamp",
        "dupe_check_flag": "0"
    },
    {
        "table_name": "reporting_occ",
        "non_nullable_col": "",
        "pk_col": "bor_client_id,option_type,symbol,rnm",
        "ignore_col": ""
    },
    {
        "table_name": "sbb_profitability",
        "non_nullable_col": "",
        "pk_col": "acct_no,account_type,rnm",
        "ignore_col": "last_insert_timestamp",
        "dupe_check_flag": "0",
        "threshold_col": "average_account_balance,capital_charge_amount,tax_amount,nii",
        "threshold_val_perc": "0.002"
    },
    {
        "table_name": "security_offset_occ",
        "non_nullable_col": "",
        "pk_col": "bor_account_id,option_bor_security_id,notional_value,option_quantity,option_investmentinstrumenttypecd,rnm",
        "ignore_col": "",
        "dupe_check_flag": "0"
    },
    {
        "table_name": "security_detail_occ",
        "non_nullable_col": "",
        "pk_col": "",
        "important_col": "cusip",
        "ignore_col": "run_date",
        "dupe_check_flag": "0"
    },
    {
        "table_name": "temp_pt_fuzzy_input",
        "non_nullable_col": "",
        "pk_col": "pt_bor_account_id",
        "ignore_col": "",
        "dupe_check_flag": "0"
    },
    {
        "table_name": "temp_rrcode_producer",
        "non_nullable_col": "",
        "pk_col": "acf2,rr_code",
        "ignore_col": "",
        "dupe_check_flag": "0"
    },
    {
        "table_name": "temp_was_client_meeting_final",
        "non_nullable_col": "",
        "pk_col": "id,acf2id,channel,activity_rm_acf2id,rm_acf2id,planner_type",
        "ignore_col": "",
        "dupe_check_flag": "0"
    },
    {
        "table_name": "temp_was_fuzzy_input",
        "non_nullable_col": "",
        "pk_col": "plan_number,rm_acf2id",
        "ignore_col": "",
        "dupe_check_flag": "0"
    },
    {
        "table_name": "temp_wca_dgr",
        "non_nullable_col": "",
        "pk_col": "",
        "important_col": "mstr_rec_id,pty_sur_key",
        "ignore_col": "",
        "dupe_check_flag": "0"
    },
    {
        "table_name": "temp_wealth_wca_acct_acf",
        "non_nullable_col": "",
        "pk_col": "bor_account_id,pty_sur_key,acf2_id",
        "ignore_col": "",
        "dupe_check_flag": "0"
    },
    {
        "table_name": "temp_wisi_fuzzy_input",
        "non_nullable_col": "",
        "pk_col": "",
        "important_col": "policy_number,rr_code",
        "ignore_col": "",
        "dupe_check_flag": "0"
    },
    {
        "table_name": "temp_wlp_fuzzy_input",
        "non_nullable_col": "",
        "pk_col": "wlp_ac_no",
        "ignore_col": "",
        "dupe_check_flag": "0"
    },
    {
        "table_name": "temp_pt_account_clean",
        "non_nullable_col": "",
        "pk_col": "",
        "important_col": "account_id",
        "ignore_col": "",
        "dupe_check_flag": "0"
    },
    {
        "table_name": "temp_wlp_client_clean",
        "non_nullable_col": "",
        "pk_col": "",
        "important_col": "wlp_ac_no",
        "ignore_col": "",
        "dupe_check_flag": "0"
    },
    {
        "table_name": "temp_wisi_active_policies",
        "non_nullable_col": "",
        "pk_col": "",
        "important_col": "plan_type,policy_number",
        "ignore_col": "",
        "dupe_check_flag": "0"
    },
    {
        "table_name": "pb_finance_cpb_loc_acct_details",
        "non_nullable_col": "",
        "pk_col": "acct_no",
        "important_col": "",
        "ignore_col": "",
        "dupe_check_flag": "0"
    },
    {
        "table_name": "pb_finance_cpb_loc_pb",
        "non_nullable_col": "",
        "pk_col": "region_name,branch_name,pb_acf2",
        "important_col": "",
        "ignore_col": "",
        "dupe_check_flag": "0",
        "threshold_col": "total_accounts,active_accounts,new_acccounts,interest,fee_amount,avg_frao_balance,avg_float_balance,breakage,origination_amortization,other_nii,slippage,fixed_cof_amount,float_cof_amount,direct_cost_amount,fee_adjust,eoe_adjust,revenue,contribution,pcl_amount,provisioned_contribution,volume,nii",
        "threshold_val_perc": "0.002"
    },
    {
        "table_name": "pb_finance_cpb_loc_branch",
        "non_nullable_col": "",
        "pk_col": "branch_cost_centre",
        "important_col": "",
        "ignore_col": "",
        "dupe_check_flag": "0",
        "threshold_col": "total_accounts,active_accounts,new_acccounts,interest,fee_amount,avg_frao_balance,avg_float_balance,breakage,origination_amortization,other_nii,slippage,fixed_cof_amount,float_cof_amount,direct_cost_amount,fee_adjust,eoe_adjust,revenue,contribution,pcl_amount,provisioned_contribution,volume,nii",
        "threshold_val_perc": "0.002"
    },
    {
        "table_name": "not_matched",
        "non_nullable_col": "",
        "pk_col": "",
        "important_col": "product_account_id,product_group",
        "ignore_col": "",
        "dupe_check_flag": "0"
    },
    {
        "table_name": "fuzzy_matches",
        "non_nullable_col": "",
        "pk_col": "",
        "important_col": "master_record_id,product_account_id,wca_bor_client_id,wca_acf2_id",
        "ignore_col": "",
        "dupe_check_flag": "0"
    },
    {
        "table_name": "temp_advisor_hierarchy",
        "non_nullable_col": "",
        "pk_col": "",
        "important_col": "acf2,rr_code,branch_lob",
        "ignore_col": "",
        "dupe_check_flag": "0"
    },
    {
        "table_name": "temp_acct_base",
        "non_nullable_col": "",
        "pk_col": "",
        "important_col": "master_record_id,account_id",
        "ignore_col": "",
        "dupe_check_flag": "0"
    },
    {
        "table_name": "temp_client_metric",
        "non_nullable_col": "",
        "pk_col": "",
        "important_col": "master_record_id,acf2,rr_code,household_id",
        "ignore_col": "",
        "dupe_check_flag": "0"
    },
    {
        "table_name": "temp_household_metric",
        "non_nullable_col": "",
        "pk_col": "",
        "important_col": "household_id,acf2,rr_code",
        "ignore_col": "",
        "dupe_check_flag": "0"
    }
]